{
  "channels": [
    {
      "username": "lh_crypto1",
      "name": "LH Crypto",
      "priority": "high",
      "language": "ru",
      "category": "telegram_gifts",
      "scrape_interval_minutes": 15,
      "is_check": false
    },
    {
      "username": "gift_newstg",
      "name": "Gift News",
      "priority": "high",
      "language": "ru",
      "category": "telegram_gifts",
      "scrape_interval_minutes": 10,
      "is_check": false
    },
    {
      "username": "detkidurova",
      "name": "Дети Дурова - Новости",
      "priority": "high",
      "language": "ru",
      "category": "telegram_gifts",
      "scrape_interval_minutes": 10,
      "is_check": false
    },
    {
      "username": "gryazniytelegram",
      "name": "ГРЯЗНЫЙ TELEGRAM",
      "priority": "high",
      "language": "ru",
      "category": "telegram_gifts",
      "scrape_interval_minutes": 10,
      "is_check": false
    },
    {
      "username": "giftsider",
      "name": "GiftSider",
      "priority": "high",
      "language": "ru",
      "category": "telegram_gifts",
      "scrape_interval_minutes": 10,
      "is_check": false
    },
    {
      "username": "gryazniytelegram",
      "name": "Gryazniy Telegram",
      "priority": "high",
      "language": "ru",
      "category": "telegram_gifts",
      "scrape_interval_minutes": 10,
      "is_check": false
    },
    {
      "username": "podarkigift",
      "name": "podarki v telegram",
      "priority": "high",
      "language": "ru",
      "category": "telegram_gifts",
      "scrape_interval_minutes": 10,
      "is_check": false
    },
    {
      "username": "groza",
      "name": "BALENCIAGA",
      "priority": "high",
      "language": "ru",
      "category": "telegram_gifts",
      "scrape_interval_minutes": 10,
      "is_check": false
    },
    {
      "username": "durovgoyda",
      "name": "Гои Дурова",
      "priority": "high",
      "language": "ru",
      "category": "telegram_gifts",
      "scrape_interval_minutes": 10,
      "is_check": false
    }
  ],
  "settings": {
    "max_posts_per_channel": 50,
    "lookback_hours": 24,
    "min_views_threshold": 100
  }
}
